{"type":"FeatureCollection","features":[{"type":"Feature","id":"current_ru_soil_moisture.1","geometry":{"type":"Point","coordinates":[12.075781,53.867291]},"geometry_name":"the_geom","properties":{"device_id":"ru-lse-20","time":"2023-05-29T07:33:02","soil_temp":20.9,"soil_mc":15.91,"soil_ec":183,"lat":53.867291,"long":12.075781}},{"type":"Feature","id":"current_ru_soil_moisture.2","geometry":{"type":"Point","coordinates":[12.07613567,53.86707517]},"geometry_name":"the_geom","properties":{"device_id":"ru-lse-25","time":"2023-05-29T14:00:02","soil_temp":21.56,"soil_mc":31.79,"soil_ec":650,"lat":53.86707517,"long":12.07613567}},{"type":"Feature","id":"current_ru_soil_moisture.3","geometry":{"type":"Point","coordinates":[12.076494,53.866935]},"geometry_name":"the_geom","properties":{"device_id":"ru-lse-27","time":"2023-05-29T17:18:07","soil_temp":17.19,"soil_mc":21.27,"soil_ec":395,"lat":53.866935,"long":12.076494}},{"type":"Feature","id":"current_ru_soil_moisture.4","geometry":{"type":"Point","coordinates":[12.076745,53.867105]},"geometry_name":"the_geom","properties":{"device_id":"ru-lse-28","time":"2023-05-29T17:10:26","soil_temp":16.83,"soil_mc":28.97,"soil_ec":2124,"lat":53.867105,"long":12.076745}},{"type":"Feature","id":"current_ru_soil_moisture.5","geometry":{"type":"Point","coordinates":[12.077512,53.866709]},"geometry_name":"the_geom","properties":{"device_id":"ru-lse-29","time":"2023-05-29T17:11:50","soil_temp":16.62,"soil_mc":15.9,"soil_ec":73,"lat":53.866709,"long":12.077512}},{"type":"Feature","id":"current_ru_soil_moisture.6","geometry":{"type":"Point","coordinates":[12.074829,53.86776]},"geometry_name":"the_geom","properties":{"device_id":"ru-lse-30","time":"2023-05-29T17:25:55","soil_temp":18.62,"soil_mc":13.98,"soil_ec":4,"lat":53.86776,"long":12.074829}}],"totalFeatures":6,"numberMatched":6,"numberReturned":6,"timeStamp":"2023-05-29T17:33:26.758Z","crs":{"type":"name","properties":{"name":"urn:ogc:def:crs:EPSG::4326"}}}